setup.py
topsis/__init__.py
topsis/topsis.py
topsis_pckg_bansalz1208.egg-info/PKG-INFO
topsis_pckg_bansalz1208.egg-info/SOURCES.txt
topsis_pckg_bansalz1208.egg-info/dependency_links.txt
topsis_pckg_bansalz1208.egg-info/top_level.txt