Metadata-Version: 2.1
Name: topsis-pckg-bansalz1208
Version: 0.0.1
Summary: it is package which tells you best value based on the data by using some mathematical calculations
Home-page: https://github.com/coolestbnslz/topsis_pckg
Author: Nikhil Bansal
Author-email: bansalz1208@gmail.com
License: UNKNOWN
Platform: UNKNOWN
Classifier: Programming Language :: Python :: 3
Classifier: License :: OSI Approved :: MIT License
Classifier: Operating System :: OS Independent
Requires-Python: >=3.6
